rtl/sram_tile/fpga_pico_bus.v
// fpga_pico_bus.v — 8-bit parallel bus controller (FPGA side)
//
// Deterministic byte-at-a-time interface between FPGA and RP2354B picos.
// Each pico gets its own bus instance. No arbitration, no contention.
//
// Protocol:
//   RX (FPGA → Pico): FPGA drives DATA, asserts RDY. Pico pulses ACK.
//   TX (Pico → FPGA): Pico drives DATA, asserts RDY. FPGA pulses ACK.
//   DIR pin owned by FPGA — selects bus direction.
//   One dead cycle on DIR change (turn-around).
//
// Frame format (both directions):
//   SOF=1 on first byte, EOF=1 on last byte.
//   SOCK[1:0] = socket/stream ID (0-3), valid with SOF.
//
// Pins per pico: DATA[7:0] + RDY + ACK + DIR + SOF + EOF + SOCK[1:0] = 15
//
// Timeout: if ACK not received within TIMEOUT_CYCLES, bus resets with error flag.
//
`default_nettype none

module fpga_pico_bus #(
    parameter FIFO_DEPTH    = 512,   // bytes per direction
    parameter TIMEOUT_CYCLES = 1024  // ACK timeout
)(
    input  wire        clk,
    input  wire        rst_n,

    // --- Physical bus pins (directly to pico GPIO) ---
    inout  wire [7:0]  bus_data,     // bidirectional data
    output reg         bus_rdy,      // sender asserts when byte valid
    input  wire        bus_ack,      // receiver pulses when byte taken
    output reg         bus_dir,      // 0=FPGA→Pico (RX), 1=Pico→FPGA (TX)
    output reg         bus_sof,      // start of frame
    output reg         bus_eof,      // end of frame
    output reg  [1:0]  bus_sock,     // socket ID

    // --- Internal FPGA interface (TX to pico) ---
    input  wire [7:0]  tx_data,      // byte to send to pico
    input  wire        tx_valid,     // byte available
    output wire        tx_ready,     // bus can accept byte
    input  wire        tx_sof,       // start of frame marker
    input  wire        tx_eof,       // end of frame marker
    input  wire [1:0]  tx_sock,      // socket for this frame

    // --- Internal FPGA interface (RX from pico) ---
    output reg  [7:0]  rx_data,      // byte received from pico
    output reg         rx_valid,     // byte available
    input  wire        rx_ready,     // downstream can accept
    output reg         rx_sof,       // start of frame
    output reg         rx_eof,       // end of frame
    output reg  [1:0]  rx_sock,      // socket ID from frame

    // --- Status ---
    output reg         timeout_err,  // ACK timeout occurred
    output reg         bus_active    // transfer in progress
);

    // ─────────────────────────────────────────────────────────────────
    // Bus direction control + tristate
    // ─────────────────────────────────────────────────────────────────
    reg [7:0] data_out;
    reg       data_oe;  // 1 = FPGA drives bus

    assign bus_data = data_oe ? data_out : 8'bz;

    // ─────────────────────────────────────────────────────────────────
    // TX FIFO (FPGA → Pico direction)
    // ─────────────────────────────────────────────────────────────────
    reg [7:0]  tx_fifo [0:FIFO_DEPTH-1];
    reg [1:0]  tx_fifo_sock [0:FIFO_DEPTH-1];
    reg        tx_fifo_sof  [0:FIFO_DEPTH-1];
    reg        tx_fifo_eof  [0:FIFO_DEPTH-1];
    reg [9:0]  tx_wptr, tx_rptr;
    wire [9:0] tx_count = tx_wptr - tx_rptr;
    wire       tx_empty = (tx_wptr == tx_rptr);
    wire       tx_full  = (tx_count == FIFO_DEPTH[9:0]);

    assign tx_ready = !tx_full;

    // TX FIFO write
    always @(posedge clk or negedge rst_n) begin
        if (!rst_n) begin
            tx_wptr <= 0;
        end else if (tx_valid && !tx_full) begin
            tx_fifo[tx_wptr[8:0]]      <= tx_data;
            tx_fifo_sock[tx_wptr[8:0]] <= tx_sock;
            tx_fifo_sof[tx_wptr[8:0]]  <= tx_sof;
            tx_fifo_eof[tx_wptr[8:0]]  <= tx_eof;
            tx_wptr <= tx_wptr + 1;
        end
    end

    // ─────────────────────────────────────────────────────────────────
    // ACK synchronizer (pico is async to FPGA clock)
    // ─────────────────────────────────────────────────────────────────
    reg ack_r, ack_rr, ack_rrr;
    wire ack_rise = ack_rr & ~ack_rrr;

    always @(posedge clk or negedge rst_n) begin
        if (!rst_n) begin
            ack_r   <= 0;
            ack_rr  <= 0;
            ack_rrr <= 0;
        end else begin
            ack_r   <= bus_ack;
            ack_rr  <= ack_r;
            ack_rrr <= ack_rr;
        end
    end

    // ─────────────────────────────────────────────────────────────────
    // Bus state machine
    // ─────────────────────────────────────────────────────────────────
    localparam [2:0] S_IDLE      = 3'd0,
                     S_TX_SETUP  = 3'd1,  // drive data, assert RDY
                     S_TX_WAIT   = 3'd2,  // wait for ACK
                     S_TX_DONE   = 3'd3,  // deassert RDY, advance FIFO
                     S_RX_WAIT   = 3'd4,  // wait for pico RDY (bus_ack reused)
                     S_RX_LATCH  = 3'd5,  // latch data, pulse ACK
                     S_TURNAROUND = 3'd6; // one dead cycle on DIR change

    reg [2:0]  state;
    reg [10:0] timeout_ctr;
    reg        prev_dir;

    always @(posedge clk or negedge rst_n) begin
        if (!rst_n) begin
            state       <= S_IDLE;
            bus_rdy     <= 0;
            bus_dir     <= 0;
            bus_sof     <= 0;
            bus_eof     <= 0;
            bus_sock    <= 0;
            data_out    <= 0;
            data_oe     <= 0;
            tx_rptr     <= 0;
            rx_data     <= 0;
            rx_valid    <= 0;
            rx_sof      <= 0;
            rx_eof      <= 0;
            rx_sock     <= 0;
            timeout_err <= 0;
            timeout_ctr <= 0;
            bus_active  <= 0;
            prev_dir    <= 0;
        end else begin
            // Default: clear single-cycle strobes
            rx_valid <= 0;

            case (state)
                S_IDLE: begin
                    bus_rdy    <= 0;
                    bus_active <= 0;
                    timeout_ctr <= 0;

                    if (!tx_empty) begin
                        // Have data to send to pico
                        if (prev_dir != 0) begin
                            bus_dir  <= 0;
                            prev_dir <= 0;
                            data_oe  <= 1;
                            state    <= S_TURNAROUND;
                        end else begin
                            data_oe <= 1;
                            state   <= S_TX_SETUP;
                        end
                    end else begin
                        // Check if pico wants to send (DIR=1, pico drives)
                        // In RX mode, we monitor bus_ack as pico's "RDY"
                        // (pico asserts its RDY on our ACK pin when DIR=1)
                        if (prev_dir != 1) begin
                            bus_dir  <= 1;
                            prev_dir <= 1;
                            data_oe  <= 0;
                            state    <= S_TURNAROUND;
                        end else begin
                            data_oe <= 0;
                            state   <= S_RX_WAIT;
                        end
                    end
                end

                S_TURNAROUND: begin
                    // One dead cycle for bus direction change
                    state <= (bus_dir == 0) ? S_TX_SETUP : S_RX_WAIT;
                end

                S_TX_SETUP: begin
                    bus_active <= 1;
                    data_out   <= tx_fifo[tx_rptr[8:0]];
                    bus_sock   <= tx_fifo_sock[tx_rptr[8:0]];
                    bus_sof    <= tx_fifo_sof[tx_rptr[8:0]];
                    bus_eof    <= tx_fifo_eof[tx_rptr[8:0]];
                    bus_rdy    <= 1;
                    timeout_ctr <= 0;
                    state      <= S_TX_WAIT;
                end

                S_TX_WAIT: begin
                    timeout_ctr <= timeout_ctr + 1;
                    if (ack_rise) begin
                        state <= S_TX_DONE;
                    end else if (timeout_ctr >= TIMEOUT_CYCLES) begin
                        timeout_err <= 1;
                        bus_rdy     <= 0;
                        state       <= S_IDLE;
                    end
                end

                S_TX_DONE: begin
                    bus_rdy <= 0;
                    bus_sof <= 0;
                    bus_eof <= 0;
                    tx_rptr <= tx_rptr + 1;
                    state   <= S_IDLE;
                end

                S_RX_WAIT: begin
                    // Pico drives DATA and asserts ACK pin (used as RDY in RX mode)
                    timeout_ctr <= timeout_ctr + 1;
                    if (ack_rise) begin
                        state <= S_RX_LATCH;
                    end else if (timeout_ctr >= TIMEOUT_CYCLES) begin
                        // No data from pico — return to idle, try TX
                        state <= S_IDLE;
                    end
                end

                S_RX_LATCH: begin
                    rx_data  <= bus_data;
                    rx_valid <= 1;
                    rx_sof   <= bus_sof;
                    rx_eof   <= bus_eof;
                    rx_sock  <= bus_sock;
                    // Pulse our RDY as ACK back to pico
                    bus_rdy  <= 1;
                    state    <= S_IDLE;
                end

                default: state <= S_IDLE;
            endcase
        end
    end

endmodule

rtl/sram_tile/tb_fpga_pico_bus.v
// tb_fpga_pico_bus.v — Testbench for 8-bit parallel bus controller
`timescale 1ns/1ps

module tb_fpga_pico_bus;

    reg        clk, rst_n;
    wire [7:0] bus_data;
    wire       bus_rdy;
    reg        bus_ack;
    wire       bus_dir;
    wire       bus_sof;
    wire       bus_eof;
    wire [1:0] bus_sock;

    // TX interface (FPGA → Pico)
    reg  [7:0] tx_data;
    reg        tx_valid;
    wire       tx_ready;
    reg        tx_sof, tx_eof;
    reg  [1:0] tx_sock;

    // RX interface (Pico → FPGA)
    wire [7:0] rx_data;
    wire       rx_valid;
    reg        rx_ready;
    wire       rx_sof, rx_eof;
    wire [1:0] rx_sock;

    wire       timeout_err;
    wire       bus_active;

    // Pico-side bus driver (simulates pico GPIO)
    reg  [7:0] pico_data_out;
    reg        pico_drive;
    assign bus_data = pico_drive ? pico_data_out : 8'bz;

    fpga_pico_bus #(
        .FIFO_DEPTH(16),
        .TIMEOUT_CYCLES(64)
    ) uut (
        .clk(clk), .rst_n(rst_n),
        .bus_data(bus_data), .bus_rdy(bus_rdy), .bus_ack(bus_ack),
        .bus_dir(bus_dir), .bus_sof(bus_sof), .bus_eof(bus_eof),
        .bus_sock(bus_sock),
        .tx_data(tx_data), .tx_valid(tx_valid), .tx_ready(tx_ready),
        .tx_sof(tx_sof), .tx_eof(tx_eof), .tx_sock(tx_sock),
        .rx_data(rx_data), .rx_valid(rx_valid), .rx_ready(rx_ready),
        .rx_sof(rx_sof), .rx_eof(rx_eof), .rx_sock(rx_sock),
        .timeout_err(timeout_err), .bus_active(bus_active)
    );

    // Clock: 50 MHz
    initial clk = 0;
    always #10 clk = ~clk;

    integer pass_count = 0;
    integer fail_count = 0;
    integer test_num = 0;

    task check(input [63:0] desc, input cond);
        begin
            test_num = test_num + 1;
            if (cond) begin
                $display("  [PASS] %0d: %0s", test_num, desc);
                pass_count = pass_count + 1;
            end else begin
                $display("  [FAIL] %0d: %0s", test_num, desc);
                fail_count = fail_count + 1;
            end
        end
    endtask

    // Simulate pico ACK after RDY (with small delay)
    task pico_ack_byte;
        begin
            @(posedge bus_rdy);
            #40;  // pico reaction time
            bus_ack = 1;
            #20;
            bus_ack = 0;
        end
    endtask

    // Simulate pico sending a byte to FPGA
    task pico_send_byte(input [7:0] data, input sof, input eof);
        begin
            // Wait for DIR=1 (RX mode)
            wait (bus_dir == 1);
            #40;
            pico_drive = 1;
            pico_data_out = data;
            // Pico uses bus_ack pin as its RDY signal when DIR=1
            bus_ack = 1;
            #20;
            bus_ack = 0;
            // Wait for FPGA to ACK (bus_rdy pulse)
            @(posedge bus_rdy);
            #20;
            pico_drive = 0;
        end
    endtask

    initial begin
        $dumpfile("tb_fpga_pico_bus.vcd");
        $dumpvars(0, tb_fpga_pico_bus);

        // Init
        rst_n = 0;
        bus_ack = 0;
        tx_data = 0;
        tx_valid = 0;
        tx_sof = 0;
        tx_eof = 0;
        tx_sock = 0;
        rx_ready = 1;
        pico_drive = 0;
        pico_data_out = 0;

        #100;
        rst_n = 1;
        #40;

        // ─────────────────────────────────────────────────────────────
        // Test 1: TX single byte (FPGA → Pico)
        // ─────────────────────────────────────────────────────────────
        $display("\n--- Test: TX single byte ---");
        tx_data = 8'hAB;
        tx_sock = 2'd1;
        tx_sof = 1;
        tx_eof = 1;
        tx_valid = 1;
        @(posedge clk); #1;
        tx_valid = 0;
        tx_sof = 0;
        tx_eof = 0;

        // Wait for bus_rdy then ACK
        pico_ack_byte;
        #60;

        check("TX ready deasserts during transfer", 1);
        check("No timeout error", !timeout_err);

        // ─────────────────────────────────────────────────────────────
        // Test 2: TX multi-byte frame
        // ─────────────────────────────────────────────────────────────
        $display("\n--- Test: TX 4-byte frame ---");
        // Load 4 bytes into FIFO
        tx_sock = 2'd2;
        tx_data = 8'h10; tx_sof = 1; tx_eof = 0; tx_valid = 1;
        @(posedge clk); #1;
        tx_data = 8'h20; tx_sof = 0; tx_eof = 0;
        @(posedge clk); #1;
        tx_data = 8'h30;
        @(posedge clk); #1;
        tx_data = 8'h40; tx_eof = 1;
        @(posedge clk); #1;
        tx_valid = 0; tx_eof = 0;

        // ACK all 4 bytes
        pico_ack_byte;
        pico_ack_byte;
        pico_ack_byte;
        pico_ack_byte;
        #100;

        check("4-byte TX frame completed", !timeout_err);
        check("Bus returns to idle", !bus_active);

        // ─────────────────────────────────────────────────────────────
        // Test 3: TX timeout (no ACK)
        // ─────────────────────────────────────────────────────────────
        $display("\n--- Test: TX timeout ---");
        tx_data = 8'hFF;
        tx_sock = 2'd0;
        tx_sof = 1; tx_eof = 1;
        tx_valid = 1;
        @(posedge clk); #1;
        tx_valid = 0; tx_sof = 0; tx_eof = 0;

        // Don't ACK — wait for timeout
        #3000;

        check("Timeout error flagged", timeout_err);

        // Reset for next tests
        rst_n = 0;
        #40;
        rst_n = 1;
        #40;

        // ─────────────────────────────────────────────────────────────
        // Test 4: RX single byte (Pico → FPGA)
        // ─────────────────────────────────────────────────────────────
        $display("\n--- Test: RX single byte ---");
        // No TX data pending, so bus should switch to RX mode
        #200;
        // Now pico sends
        pico_send_byte(8'hCD, 1, 1);
        // Wait a few clocks for rx_valid pulse
        #200;

        // rx_valid is single-cycle, check rx_data which persists
        check("RX byte received", rx_data == 8'hCD);
        check("RX data correct", rx_data == 8'hCD);

        // ─────────────────────────────────────────────────────────────
        // Test 5: Bidirectional interleave
        // ─────────────────────────────────────────────────────────────
        $display("\n--- Test: Bidirectional ---");
        // Queue TX
        tx_data = 8'hEE; tx_sock = 2'd3; tx_sof = 1; tx_eof = 1; tx_valid = 1;
        @(posedge clk); #1;
        tx_valid = 0; tx_sof = 0; tx_eof = 0;

        // ACK it
        pico_ack_byte;
        #100;

        check("Bidir TX completed", !timeout_err);

        // ─────────────────────────────────────────────────────────────
        // Test 6: FIFO full backpressure
        // ─────────────────────────────────────────────────────────────
        $display("\n--- Test: FIFO backpressure ---");
        // Fill FIFO (16 deep)
        begin : fill_fifo
            integer i;
            for (i = 0; i < 16; i = i + 1) begin
                tx_data = i[7:0]; tx_valid = 1;
                tx_sof = (i == 0); tx_eof = (i == 15);
                tx_sock = 2'd0;
                @(posedge clk); #1;
            end
            tx_valid = 0; tx_sof = 0; tx_eof = 0;
        end

        check("FIFO full, tx_ready=0", !tx_ready);

        // Drain by ACKing
        begin : drain_fifo
            integer j;
            for (j = 0; j < 16; j = j + 1) begin
                pico_ack_byte;
            end
        end
        #100;

        check("FIFO drained, tx_ready=1", tx_ready);

        // ─────────────────────────────────────────────────────────────
        // Test 7: Reset clears state
        // ─────────────────────────────────────────────────────────────
        $display("\n--- Test: Reset ---");
        tx_data = 8'h99; tx_valid = 1; tx_sof = 1; tx_eof = 1; tx_sock = 0;
        @(posedge clk); #1;
        tx_valid = 0; tx_sof = 0; tx_eof = 0;
        #20;
        rst_n = 0;
        #40;
        rst_n = 1;
        #40;

        check("Reset clears timeout_err", !timeout_err);
        check("Reset clears bus_active", !bus_active);

        // ─────────────────────────────────────────────────────────────
        // Summary
        // ─────────────────────────────────────────────────────────────
        #100;
        $display("\n══════════════════════════════════════");
        $display("  Results: %0d PASS, %0d FAIL / %0d total",
                 pass_count, fail_count, test_num);
        $display("══════════════════════════════════════\n");
        if (fail_count == 0)
            $display("  *** ALL TESTS PASSED ***\n");
        else
            $display("  *** FAILURES DETECTED ***\n");
        $finish;
    end

endmodule

rtl/sram_tile/tb_fpga_pico_bus.vcd
$date
	Wed Apr 29 23:23:39 2026
$end
$version
	Icarus Verilog
$end
$timescale
	1ps
$end
$scope module tb_fpga_pico_bus $end
$var wire 8 ! bus_data [7:0] $end
$var wire 1 " tx_ready $end
$var wire 1 # timeout_err $end
$var wire 1 $ rx_valid $end
$var wire 1 % rx_sof $end
$var wire 2 & rx_sock [1:0] $end
$var wire 1 ' rx_eof $end
$var wire 8 ( rx_data [7:0] $end
$var wire 1 ) bus_sof $end
$var wire 2 * bus_sock [1:0] $end
$var wire 1 + bus_rdy $end
$var wire 1 , bus_eof $end
$var wire 1 - bus_dir $end
$var wire 1 . bus_active $end
$var reg 1 / bus_ack $end
$var reg 1 0 clk $end
$var reg 8 1 pico_data_out [7:0] $end
$var reg 1 2 pico_drive $end
$var reg 1 3 rst_n $end
$var reg 1 4 rx_ready $end
$var reg 8 5 tx_data [7:0] $end
$var reg 1 6 tx_eof $end
$var reg 2 7 tx_sock [1:0] $end
$var reg 1 8 tx_sof $end
$var reg 1 9 tx_valid $end
$var integer 32 : fail_count [31:0] $end
$var integer 32 ; pass_count [31:0] $end
$var integer 32 < test_num [31:0] $end
$scope module uut $end
$var wire 1 = ack_rise $end
$var wire 1 / bus_ack $end
$var wire 8 > bus_data [7:0] $end
$var wire 1 0 clk $end
$var wire 1 3 rst_n $end
$var wire 1 4 rx_ready $end
$var wire 8 ? tx_data [7:0] $end
$var wire 1 6 tx_eof $end
$var wire 2 @ tx_sock [1:0] $end
$var wire 1 8 tx_sof $end
$var wire 1 9 tx_valid $end
$var wire 1 " tx_ready $end
$var wire 1 A tx_full $end
$var wire 1 B tx_empty $end
$var wire 10 C tx_count [9:0] $end
$var parameter 32 D FIFO_DEPTH $end
$var parameter 3 E S_IDLE $end
$var parameter 3 F S_RX_LATCH $end
$var parameter 3 G S_RX_WAIT $end
$var parameter 3 H S_TURNAROUND $end
$var parameter 3 I S_TX_DONE $end
$var parameter 3 J S_TX_SETUP $end
$var parameter 3 K S_TX_WAIT $end
$var parameter 32 L TIMEOUT_CYCLES $end
$var reg 1 M ack_r $end
$var reg 1 N ack_rr $end
$var reg 1 O ack_rrr $end
$var reg 1 . bus_active $end
$var reg 1 - bus_dir $end
$var reg 1 , bus_eof $end
$var reg 1 + bus_rdy $end
$var reg 2 P bus_sock [1:0] $end
$var reg 1 ) bus_sof $end
$var reg 1 Q data_oe $end
$var reg 8 R data_out [7:0] $end
$var reg 1 S prev_dir $end
$var reg 8 T rx_data [7:0] $end
$var reg 1 ' rx_eof $end
$var reg 2 U rx_sock [1:0] $end
$var reg 1 % rx_sof $end
$var reg 1 $ rx_valid $end
$var reg 3 V state [2:0] $end
$var reg 11 W timeout_ctr [10:0] $end
$var reg 1 # timeout_err $end
$var reg 10 X tx_rptr [9:0] $end
$var reg 10 Y tx_wptr [9:0] $end
$upscope $end
$scope begin drain_fifo $end
$var integer 32 Z j [31:0] $end
$upscope $end
$scope begin fill_fifo $end
$var integer 32 [ i [31:0] $end
$upscope $end
$scope task check $end
$var reg 1 \ cond $end
$var reg 64 ] desc [63:0] $end
$upscope $end
$scope task pico_ack_byte $end
$upscope $end
$scope task pico_send_byte $end
$var reg 8 ^ data [7:0] $end
$var reg 1 _ eof $end
$var reg 1 ` sof $end
$upscope $end
$upscope $end
$enddefinitions $end
$comment Show the parameter values. $end
$dumpall
b1000000 L
b10 K
b1 J
b11 I
b110 H
b100 G
b101 F
b0 E
b10000 D
$end
#0
$dumpvars
x`
x_
bx ^
bx ]
x\
bx [
bx Z
b0 Y
b0 X
b0 W
b0 V
b0 U
b0 T
0S
b0 R
0Q
b0 P
0O
0N
0M
b0 C
1B
0A
b0 @
b0 ?
bz >
0=
b0 <
b0 ;
b0 :
09
08
b0 7
06
b0 5
14
03
02
b0 1
00
0/
0.
0-
0,
0+
b0 *
0)
b0 (
0'
b0 &
0%
0$
0#
1"
bz !
$end
#10000
10
#20000
00
#30000
10
#40000
00
#50000
10
#60000
00
#70000
10
#80000
00
#90000
10
#100000
00
13
#110000
b110 V
1S
1-
10
#120000
00
#130000
b100 V
10
#140000
00
19
16
18
b1 7
b1 @
b10101011 5
b10101011 ?
#150000
b1 C
0B
b1 Y
b1 W
10
#151000
06
08
09
#160000
00
#170000
b10 W
10
#180000
00
#190000
b11 W
10
#200000
00
#210000
b100 W
10
#220000
00
#230000
b101 W
10
#240000
00
#250000
b110 W
10
#260000
00
#270000
b111 W
10
#280000
00
#290000
b1000 W
10
#300000
00
#310000
b1001 W
10
#320000
00
#330000
b1010 W
10
#340000
00
#350000
b1011 W
10
#360000
00
#370000
b1100 W
10
#380000
00
#390000
b1101 W
10
#400000
00
#410000
b1110 W
10
#420000
00
#430000
b1111 W
10
#440000
00
#450000
b10000 W
10
#460000
00
#470000
b10001 W
10
#480000
00
#490000
b10010 W
10
#500000
00
#510000
b10011 W
10
#520000
00
#530000
b10100 W
10
#540000
00
#550000
b10101 W
10
#560000
00
#570000
b10110 W
10
#580000
00
#590000
b10111 W
10
#600000
00
#610000
b11000 W
10
#620000
00
#630000
b11001 W
10
#640000
00
#650000
b11010 W
10
#660000
00
#670000
b11011 W
10
#680000
00
#690000
b11100 W
10
#700000
00
#710000
b11101 W
10
#720000
00
#730000
b11110 W
10
#740000
00
#750000
b11111 W
10
#760000
00
#770000
b100000 W
10
#780000
00
#790000
b100001 W
10
#800000
00
#810000
b100010 W
10
#820000
00
#830000
b100011 W
10
#840000
00
#850000
b100100 W
10
#860000
00
#870000
b100101 W
10
#880000
00
#890000
b100110 W
10
#900000
00
#910000
b100111 W
10
#920000
00
#930000
b101000 W
10
#940000
00
#950000
b101001 W
10
#960000
00
#970000
b101010 W
10
#980000
00
#990000
b101011 W
10
#1000000
00
#1010000
b101100 W
10
#1020000
00
#1030000
b101101 W
10
#1040000
00
#1050000
b101110 W
10
#1060000
00
#1070000
b101111 W
10
#1080000
00
#1090000
b110000 W
10
#1100000
00
#1110000
b110001 W
10
#1120000
00
#1130000
b110010 W
10
#1140000
00
#1150000
b110011 W
10
#1160000
00
#1170000
b110100 W
10
#1180000
00
#1190000
b110101 W
10
#1200000
00
#1210000
b110110 W
10
#1220000
00
#1230000
b110111 W
10
#1240000
00
#1250000
b111000 W
10
#1260000
00
#1270000
b111001 W
10
#1280000
00
#1290000
b111010 W
10
#1300000
00
#1310000
b111011 W
10
#1320000
00
#1330000
b111100 W
10
#1340000
00
#1350000
b111101 W
10
#1360000
00
#1370000
b111110 W
10
#1380000
00
#1390000
b111111 W
10
#1400000
00
#1410000
b1000000 W
10
#1420000
00
#1430000
b0 V
b1000001 W
10
#1440000
00
#1450000
b0 !
b0 >
b110 V
1Q
0S
0-
b0 W
10
#1460000
00
#1470000
b1 V
10
#1480000
00
#1490000
b10101011 !
b10101011 >
b10 V
1+
1,
1)
b1 *
b1 P
b10101011 R
1.
10
#1500000
00
#1510000
b1 W
10
#1520000
00
#1530000
b10 W
1M
10
1/
#1540000
00
#1550000
1=
1N
0M
b11 W
10
0/
#1560000
00
#1570000
0=
b11 V
b100 W
1O
0N
10
#1580000
00
#1590000
0O
b0 V
b0 C
1B
b1 X
0,
0)
0+
10
#1600000
00
#1610000
bz !
bz >
b110 V
0Q
1S
1-
b0 W
0.
b1 C
0B
b10 Y
10
19
18
b10000 5
b10000 ?
b10 7
b10 @
b10 ;
b10 <
1\
b111010101110100001000000110010101110010011100100110111101110010 ]
#1611000
08
b100000 5
b100000 ?
#1620000
00
#1630000
b10 C
b11 Y
b100 V
10
#1631000
b110000 5
b110000 ?
#1640000
00
#1650000
b1 W
b11 C
b100 Y
10
#1651000
16
b1000000 5
b1000000 ?
#1660000
00
#1670000
b100 C
b101 Y
b10 W
10
#1671000
06
09
#1680000
00
#1690000
b11 W
10
#1700000
00
#1710000
b100 W
10
#1720000
00
#1730000
b101 W
10
#1740000
00
#1750000
b110 W
10
#1760000
00
#1770000
b111 W
10
#1780000
00
#1790000
b1000 W
10
#1800000
00
#1810000
b1001 W
10
#1820000
00
#1830000
b1010 W
10
#1840000
00
#1850000
b1011 W
10
#1860000
00
#1870000
b1100 W
10
#1880000
00
#1890000
b1101 W
10
#1900000
00
#1910000
b1110 W
10
#1920000
00
#1930000
b1111 W
10
#1940000
00
#1950000
b10000 W
10
#1960000
00
#1970000
b10001 W
10
#1980000
00
#1990000
b10010 W
10
#2000000
00
#2010000
b10011 W
10
#2020000
00
#2030000
b10100 W
10
#2040000
00
#2050000
b10101 W
10
#2060000
00
#2070000
b10110 W
10
#2080000
00
#2090000
b10111 W
10
#2100000
00
#2110000
b11000 W
10
#2120000
00
#2130000
b11001 W
10
#2140000
00
#2150000
b11010 W
10
#2160000
00
#2170000
b11011 W
10
#2180000
00
#2190000
b11100 W
10
#2200000
00
#2210000
b11101 W
10
#2220000
00
#2230000
b11110 W
10
#2240000
00
#2250000
b11111 W
10
#2260000
00
#2270000
b100000 W
10
#2280000
00
#2290000
b100001 W
10
#2300000
00
#2310000
b100010 W
10
#2320000
00
#2330000
b100011 W
10
#2340000
00
#2350000
b100100 W
10
#2360000
00
#2370000
b100101 W
10
#2380000
00
#2390000
b100110 W
10
#2400000
00
#2410000
b100111 W
10
#2420000
00
#2430000
b101000 W
10
#2440000
00
#2450000
b101001 W
10
#2460000
00
#2470000
b101010 W
10
#2480000
00
#2490000
b101011 W
10
#2500000
00
#2510000
b101100 W
10
#2520000
00
#2530000
b101101 W
10
#2540000
00
#2550000
b101110 W
10
#2560000
00
#2570000
b101111 W
10
#2580000
00
#2590000
b110000 W
10
#2600000
00
#2610000
b110001 W
10
#2620000
00
#2630000
b110010 W
10
#2640000
00
#2650000
b110011 W
10
#2660000
00
#2670000
b110100 W
10
#2680000
00
#2690000
b110101 W
10
#2700000
00
#2710000
b110110 W
10
#2720000
00
#2730000
b110111 W
10
#2740000
00
#2750000
b111000 W
10
#2760000
00
#2770000
b111001 W
10
#2780000
00
#2790000
b111010 W
10
#2800000
00
#2810000
b111011 W
10
#2820000
00
#2830000
b111100 W
10
#2840000
00
#2850000
b111101 W
10
#2860000
00
#2870000
b111110 W
10
#2880000
00
#2890000
b111111 W
10
#2900000
00
#2910000
b1000000 W
10
#2920000
00
#2930000
b0 V
b1000001 W
10
#2940000
00
#2950000
b10101011 !
b10101011 >
b110 V
1Q
0S
0-
b0 W
10
#2960000
00
#2970000
b1 V
10
#2980000
00
#2990000
b10000 !
b10000 >
b10 V
1+
1)
b10 *
b10 P
b10000 R
1.
10
#3000000
00
#3010000
b1 W
10
#3020000
00
#3030000
1M
b10 W
10
1/
#3040000
00
#3050000
1=
b11 W
1N
0M
10
0/
#3060000
00
#3070000
0=
1O
0N
b11 V
b100 W
10
#3080000
00
#3090000
b0 V
b11 C
b10 X
0)
0+
0O
10
#3100000
00
#3110000
b1 V
b0 W
0.
10
#3120000
00
#3130000
b100000 !
b100000 >
b10 V
1+
b100000 R
1.
10
#3140000
00
#3150000
b1 W
10
#3160000
00
#3170000
b10 W
1M
10
1/
#3180000
00
#3190000
1=
1N
0M
b11 W
10
0/
#3200000
00
#3210000
0=
b11 V
b100 W
1O
0N
10
#3220000
00
#3230000
0O
b0 V
b10 C
b11 X
0+
10
#3240000
00
#3250000
b1 V
b0 W
0.
10
#3260000
00
#3270000
b110000 !
b110000 >
b10 V
1+
b110000 R
1.
10
#3280000
00
#3290000
b1 W
10
#3300000
00
#3310000
1M
b10 W
10
1/
#3320000
00
#3330000
1=
b11 W
1N
0M
10
0/
#3340000
00
#3350000
0=
1O
0N
b11 V
b100 W
10
#3360000
00
#3370000
b0 V
b1 C
b100 X
0+
0O
10
#3380000
00
#3390000
b1 V
b0 W
0.
10
#3400000
00
#3410000
b1000000 !
b1000000 >
b10 V
1+
1,
b1000000 R
1.
10
#3420000
00
#3430000
b1 W
10
#3440000
00
#3450000
b10 W
1M
10
1/
#3460000
00
#3470000
1=
1N
0M
b11 W
10
0/
#3480000
00
#3490000
0=
b11 V
b100 W
1O
0N
10
#3500000
00
#3510000
0O
b0 V
b0 C
1B
b101 X
0,
0+
10
#3520000
00
#3530000
bz !
bz >
b110 V
0Q
1S
1-
b0 W
0.
10
#3540000
00
#3550000
b100 V
10
#3560000
00
#3570000
b1 W
b1 C
0B
b110 Y
10
19
16
18
b0 7
b0 @
b11111111 5
b11111111 ?
b100 ;
b100 <
b10000001110100011011110010000001101001011001000110110001100101 ]
#3571000
06
08
09
#3580000
00
#3590000
b10 W
10
#3600000
00
#3610000
b11 W
10
#3620000
00
#3630000
b100 W
10
#3640000
00
#3650000
b101 W
10
#3660000
00
#3670000
b110 W
10
#3680000
00
#3690000
b111 W
10
#3700000
00
#3710000
b1000 W
10
#3720000
00
#3730000
b1001 W
10
#3740000
00
#3750000
b1010 W
10
#3760000
00
#3770000
b1011 W
10
#3780000
00
#3790000
b1100 W
10
#3800000
00
#3810000
b1101 W
10
#3820000
00
#3830000
b1110 W
10
#3840000
00
#3850000
b1111 W
10
#3860000
00
#3870000
b10000 W
10
#3880000
00
#3890000
b10001 W
10
#3900000
00
#3910000
b10010 W
10
#3920000
00
#3930000
b10011 W
10
#3940000
00
#3950000
b10100 W
10
#3960000
00
#3970000
b10101 W
10
#3980000
00
#3990000
b10110 W
10
#4000000
00
#4010000
b10111 W
10
#4020000
00
#4030000
b11000 W
10
#4040000
00
#4050000
b11001 W
10
#4060000
00
#4070000
b11010 W
10
#4080000
00
#4090000
b11011 W
10
#4100000
00
#4110000
b11100 W
10
#4120000
00
#4130000
b11101 W
10
#4140000
00
#4150000
b11110 W
10
#4160000
00
#4170000
b11111 W
10
#4180000
00
#4190000
b100000 W
10
#4200000
00
#4210000
b100001 W
10
#4220000
00
#4230000
b100010 W
10
#4240000
00
#4250000
b100011 W
10
#4260000
00
#4270000
b100100 W
10
#4280000
00
#4290000
b100101 W
10
#4300000
00
#4310000
b100110 W
10
#4320000
00
#4330000
b100111 W
10
#4340000
00
#4350000
b101000 W
10
#4360000
00
#4370000
b101001 W
10
#4380000
00
#4390000
b101010 W
10
#4400000
00
#4410000
b101011 W
10
#4420000
00
#4430000
b101100 W
10
#4440000
00
#4450000
b101101 W
10
#4460000
00
#4470000
b101110 W
10
#4480000
00
#4490000
b101111 W
10
#4500000
00
#4510000
b110000 W
10
#4520000
00
#4530000
b110001 W
10
#4540000
00
#4550000
b110010 W
10
#4560000
00
#4570000
b110011 W
10
#4580000
00
#4590000
b110100 W
10
#4600000
00
#4610000
b110101 W
10
#4620000
00
#4630000
b110110 W
10
#4640000
00
#4650000
b110111 W
10
#4660000
00
#4670000
b111000 W
10
#4680000
00
#4690000
b111001 W
10
#4700000
00
